{
    "$schema": "https://schema.management.azure.com/schemas/2015-01-01/deploymentParameters.json#",
    "contentVersion": "1.0.0.0",
    "parameters": {
        "location": {
            "value": "australiaeast"
        },
        "extendedLocation": {
            "value": {}
        },
        "virtualNetworkName": {
            "value": "lbvnet"
        },
        "resourceGroup": {
            "value": "ssvr"
        },
        "addressSpaces": {
            "value": [
                "10.0.0.0/24"
            ]
        },
        "ipv6Enabled": {
            "value": false
        },
        "subnetCount": {
            "value": 1
        },
        "subnet0_name": {
            "value": "ilbsubnet"
        },
        "subnet0_addressRange": {
            "value": "10.0.0.0/29"
        },
        "ddosProtectionPlanEnabled": {
            "value": false
        },
        "firewallEnabled": {
            "value": false
        },
        "bastionEnabled": {
            "value": false
        }
    }
}
